telegram_log/__init__.py
telegram_log/handler.py
telegram_log-1.0.14.dist-info/WHEEL
telegram_log-1.0.14.dist-info/METADATA
telegram_log-1.0.14.dist-info/RECORD
